openfilter/__init__.py
openfilter/cli/__init__.py
openfilter/cli/__main__.py
openfilter/cli/cmd_info.py
openfilter/cli/cmd_run.py
openfilter/cli/common.py
openfilter/filter_runtime/__init__.py
openfilter/filter_runtime/dlcache.py
openfilter/filter_runtime/filter.py
openfilter/filter_runtime/frame.py
openfilter/filter_runtime/logging.py
openfilter/filter_runtime/metrics.py
openfilter/filter_runtime/mq.py
openfilter/filter_runtime/rolllog.py
openfilter/filter_runtime/test.py
openfilter/filter_runtime/utils.py
openfilter/filter_runtime/zeromq.py
openfilter/filter_runtime/filters/__init__.py
openfilter/filter_runtime/filters/image_in.py
openfilter/filter_runtime/filters/image_out.py
openfilter/filter_runtime/filters/mqtt_out.py
openfilter/filter_runtime/filters/recorder.py
openfilter/filter_runtime/filters/rest.py
openfilter/filter_runtime/filters/util.py
openfilter/filter_runtime/filters/video.py
openfilter/filter_runtime/filters/video_in.py
openfilter/filter_runtime/filters/video_out.py
openfilter/filter_runtime/filters/webvis.py
openfilter/filter_runtime/open_telemetry/__init__.py
openfilter/filter_runtime/open_telemetry/open_telemetry_client.py
openfilter/filter_runtime/open_telemetry/open_telemetry_exporter_factory.py
openfilter/lineage/__init__.py
openfilter/lineage/openlineage_client.py
openfilter/lineage/schema/OpenFilterConfigRunFacet.json
openfilter/observability/__init__.py
openfilter/observability/bridge.py
openfilter/observability/client.py
openfilter/observability/config.py
openfilter/observability/lineage.py
openfilter/observability/registry.py
openfilter/observability/specs.py
openfilter/observability/schema/OpenFilterConfigRunFacet.json
openfilter-0.1.14.dist-info/licenses/LICENSE
openfilter-0.1.14.dist-info/METADATA
openfilter-0.1.14.dist-info/WHEEL
openfilter-0.1.14.dist-info/entry_points.txt
openfilter-0.1.14.dist-info/top_level.txt
openfilter-0.1.14.dist-info/RECORD
