Metadata-Version: 2.4
Name: openfilter
Version: 0.1.14
License-Expression: Apache-2.0
Classifier: Programming Language :: Python :: 3
Classifier: Programming Language :: Python :: 3.10
Classifier: Programming Language :: Python :: 3.11
Classifier: Programming Language :: Python :: 3.12
Classifier: Programming Language :: Python :: 3.13
Requires-Python: <3.14,>=3.10
License-File: LICENSE
Requires-Dist: numpy==1.26.4
Requires-Dist: opencv-python-headless==4.10.0.84
Requires-Dist: psutil==5.9.8
Requires-Dist: pyzmq==26.2.0
Requires-Dist: openlineage-python==1.33.0
Requires-Dist: requests==2.32.4
Requires-Dist: opentelemetry-api==1.34.1
Requires-Dist: opentelemetry-exporter-gcp-monitoring==1.9.0a0
Requires-Dist: opentelemetry-exporter-otlp==1.34.1
Requires-Dist: opentelemetry-exporter-otlp-proto-common==1.34.1
Requires-Dist: opentelemetry-exporter-otlp-proto-grpc==1.34.1
Requires-Dist: opentelemetry-exporter-otlp-proto-http==1.34.1
Requires-Dist: opentelemetry-proto==1.34.1
Requires-Dist: opentelemetry-resourcedetector-gcp==1.9.0a0
Requires-Dist: opentelemetry-sdk==1.34.1
Requires-Dist: opentelemetry-semantic-conventions==0.55b1
Provides-Extra: dev
Requires-Dist: build==1.2.1; extra == "dev"
Requires-Dist: docker==7.1.0; extra == "dev"
Requires-Dist: setuptools==72.2.0; extra == "dev"
Requires-Dist: twine<7,>=6.1.0; extra == "dev"
Requires-Dist: wheel==0.44.0; extra == "dev"
Requires-Dist: pytest==8.3.4; extra == "dev"
Requires-Dist: jq==1.8.0; extra == "dev"
Requires-Dist: pytest-cov==6.0.0; extra == "dev"
Provides-Extra: mqtt-out
Requires-Dist: paho-mqtt==1.6.1; extra == "mqtt-out"
Requires-Dist: setuptools==72.2.0; extra == "mqtt-out"
Provides-Extra: recorder
Provides-Extra: rest
Requires-Dist: fastapi==0.89.0; extra == "rest"
Requires-Dist: uvicorn==0.20.0; extra == "rest"
Requires-Dist: python-multipart==0.0.9; extra == "rest"
Provides-Extra: util
Provides-Extra: video
Provides-Extra: video-in
Requires-Dist: setuptools==72.2.0; extra == "video-in"
Requires-Dist: vidgear[core]==0.3.3; extra == "video-in"
Requires-Dist: boto3>=1.26.0; extra == "video-in"
Provides-Extra: video-out
Requires-Dist: setuptools==72.2.0; extra == "video-out"
Requires-Dist: vidgear[core]==0.3.3; extra == "video-out"
Provides-Extra: webvis
Requires-Dist: fastapi==0.89.0; extra == "webvis"
Requires-Dist: uvicorn==0.20.0; extra == "webvis"
Provides-Extra: all
Requires-Dist: setuptools==72.2.0; extra == "all"
Requires-Dist: paho-mqtt==1.6.1; extra == "all"
Requires-Dist: fastapi==0.89.0; extra == "all"
Requires-Dist: uvicorn==0.20.0; extra == "all"
Requires-Dist: python-multipart==0.0.9; extra == "all"
Requires-Dist: google-cloud-monitoring==2.22.2; extra == "all"
Requires-Dist: google-cloud-storage==2.17.0; extra == "all"
Requires-Dist: vidgear[core]==0.3.3; extra == "all"
Requires-Dist: boto3>=1.26.0; extra == "all"
Dynamic: license-file
